cascadecmsdriver/__init__.py
cascadecmsdriver/cmstypes.py
cascadecmsdriver/driver.py
cascadecmsdriver/test.py
py_cascade_cms_api-1.1.3.dist-info/LICENSE.md
py_cascade_cms_api-1.1.3.dist-info/METADATA
py_cascade_cms_api-1.1.3.dist-info/WHEEL
py_cascade_cms_api-1.1.3.dist-info/top_level.txt
py_cascade_cms_api-1.1.3.dist-info/RECORD
