Metadata-Version: 2.1
Name: py-cascade-cms-api
Version: 1.1.3
Summary: Simplify interaction with Hannon Hill's Cascade CMS 8 REST API
Home-page: https://github.com/austinjhunt/CascadeCMS
Author: Austin Hunt
Author-email: austin353@gmail.com
License: MIT
Project-URL: Documentation, https://github.com/austinjhunt/CascadeCMS
Project-URL: Bug Reports, https://github.com/austinjhunt/CascadeCMS/issues
Project-URL: Source Code, https://github.com/austinjhunt/CascadeCMS
Project-URL: Cascade CMS REST API Docs, https://www.hannonhill.com/cascadecms/latest/developing-in-cascade/rest-api/index.html
Keywords: cascade,cms,rest,api,hannon hill,driver
Platform: UNKNOWN
Classifier: Intended Audience :: System Administrators
Classifier: Topic :: Software Development :: Libraries :: Python Modules
Classifier: Programming Language :: Python :: 3.6
Classifier: Programming Language :: Python :: 3.7
Classifier: Programming Language :: Python :: 3.8
Classifier: Programming Language :: Python :: 3.9
Classifier: Programming Language :: Python :: 3.10
Classifier: Programming Language :: Python :: 3 :: Only
Classifier: License :: OSI Approved :: MIT License
Classifier: Operating System :: OS Independent
Requires-Python: >=3.6
License-File: LICENSE.md
Requires-Dist: requests
Requires-Dist: uplink
